hcbl/Hachi_filter.py
hcbl/__init__.py
hcbl/blacklist.py
hcbl/test_for_bl.py
hcbl/wu_manber.py
hcbl-0.0.2.dist-info/DESCRIPTION.rst
hcbl-0.0.2.dist-info/METADATA
hcbl-0.0.2.dist-info/RECORD
hcbl-0.0.2.dist-info/WHEEL
hcbl-0.0.2.dist-info/metadata.json
hcbl-0.0.2.dist-info/top_level.txt
