Metadata-Version: 2.0
Name: hcbl
Version: 0.0.2
Summary: A plugin for Hachi to block spam words.
Home-page: https://github.com/guokr/Hachi
Author: MomingCoder
Author-email: a398445075@gmail.com
License: MIT
Keywords: filter,Hachi,plugin,blacklist
Platform: UNKNOWN
Classifier: Topic :: Text Processing
